lexnlp/__init__.py
lexnlp/config/__init__.py
lexnlp/config/stanford.py
lexnlp/config/de/de_courts.csv
lexnlp/config/en/__init__.py
lexnlp/config/en/au_courts.csv
lexnlp/config/en/ca_courts.csv
lexnlp/config/en/company_types.csv
lexnlp/config/en/company_types.py
lexnlp/config/en/geoentities_config.py
lexnlp/config/en/us_courts.csv
lexnlp/config/en/us_state_courts.csv
lexnlp/config/es/es_courts.csv
lexnlp/config/es/es_regulations.csv
lexnlp/extract/__init__.py
lexnlp/extract/all_locales/__init__.py
lexnlp/extract/all_locales/amounts.py
lexnlp/extract/all_locales/citations.py
lexnlp/extract/all_locales/copyrights.py
lexnlp/extract/all_locales/court_citations.py
lexnlp/extract/all_locales/courts.py
lexnlp/extract/all_locales/dates.py
lexnlp/extract/all_locales/definitions.py
lexnlp/extract/all_locales/durations.py
lexnlp/extract/all_locales/geoentities.py
lexnlp/extract/all_locales/languages.py
lexnlp/extract/all_locales/money.py
lexnlp/extract/all_locales/percents.py
lexnlp/extract/common/__init__.py
lexnlp/extract/common/annotation_locator_type.py
lexnlp/extract/common/annotation_type.py
lexnlp/extract/common/base_path.py
lexnlp/extract/common/dates.py
lexnlp/extract/common/dates_classifier_model.py
lexnlp/extract/common/fact_extracting.py
lexnlp/extract/common/geoentity_detector.py
lexnlp/extract/common/language_dictionary_reader.py
lexnlp/extract/common/money_detector.py
lexnlp/extract/common/pattern_found.py
lexnlp/extract/common/special_characters.py
lexnlp/extract/common/text_beautifier.py
lexnlp/extract/common/text_pattern_collector.py
lexnlp/extract/common/universal_court_parser.py
lexnlp/extract/common/year_parser.py
lexnlp/extract/common/annotations/__init__.py
lexnlp/extract/common/annotations/act_annotation.py
lexnlp/extract/common/annotations/address_annotation.py
lexnlp/extract/common/annotations/amount_annotation.py
lexnlp/extract/common/annotations/citation_annotation.py
lexnlp/extract/common/annotations/company_annotation.py
openlegal_lexnlp-2.2.1.0.dist-info/LICENSE
openlegal_lexnlp-2.2.1.0.dist-info/METADATA
openlegal_lexnlp-2.2.1.0.dist-info/WHEEL
openlegal_lexnlp-2.2.1.0.dist-info/top_level.txt
openlegal_lexnlp-2.2.1.0.dist-info/RECORD
