Metadata-Version: 2.1
Name: openlegal-lexnlp
Version: 2.2.1.0
Summary: LexPredict LexNLP
Home-page: https://contraxsuite.com
Author: ContraxSuite, LLC
Author-email: support@contraxsuite.com
License: AGPL
Keywords: legal contract document analytics nlp ml machine learning natural language
Classifier: Development Status :: 4 - Beta
Classifier: Intended Audience :: Information Technology
Classifier: Intended Audience :: Legal Industry
Classifier: Intended Audience :: Developers
Classifier: License :: OSI Approved :: GNU Affero General Public License v3
Classifier: License :: Other/Proprietary License
Classifier: Programming Language :: Python :: 3.8
Classifier: Natural Language :: English
Classifier: Topic :: Office/Business
Classifier: Topic :: Text Processing :: Linguistic
Requires-Python: ~=3.6
License-File: LICENSE
Requires-Dist: cloudpickle (==2.1.0)
Requires-Dist: dateparser (==1.1.1)
Requires-Dist: gensim (==4.1.2)
Requires-Dist: joblib (==1.1.0)
Requires-Dist: nltk (==3.7)
Requires-Dist: num2words (==0.5.10)
Requires-Dist: numpy (==1.22.4)
Requires-Dist: pandas (==1.4.2)
Requires-Dist: pycountry (==22.3.5)
Requires-Dist: regex (==2022.3.2)
Requires-Dist: reporters-db (==3.2.18)
Requires-Dist: requests (==2.27.1)
Requires-Dist: scipy (==1.8.1)
Requires-Dist: scikit-learn (==0.23.1)
Requires-Dist: tzlocal (==2.1)
Requires-Dist: tqdm (>=4.36.0)
Requires-Dist: Unidecode (==1.3.4)
Requires-Dist: us (==2.0.2)
Requires-Dist: zahlwort2num (==0.3.0)
Provides-Extra: dev
Requires-Dist: pytest (>=2.8.5) ; extra == 'dev'
Requires-Dist: mock ; extra == 'dev'
Requires-Dist: pytz (>=2015.7) ; extra == 'dev'
Requires-Dist: nose ; extra == 'dev'
Requires-Dist: memory-profiler ; extra == 'dev'
Requires-Dist: psutil ; extra == 'dev'
Requires-Dist: matplotlib ; extra == 'dev'
Provides-Extra: test
Requires-Dist: pytest (>=2.8.5) ; extra == 'test'
Requires-Dist: mock ; extra == 'test'
Requires-Dist: pytz (>=2015.7) ; extra == 'test'
Requires-Dist: nose ; extra == 'test'
Requires-Dist: memory-profiler ; extra == 'test'
Requires-Dist: psutil ; extra == 'test'
